globaleaks_ephemeral_fs/__init__.py
globaleaks_ephemeral_fs/ephemeral_fs.py
globaleaks_ephemeral_fs/main.py
globaleaks_ephemeral_fs/secure_temporary_file.py
test_evilaliv3-0.0.5.dist-info/LICENSE
test_evilaliv3-0.0.5.dist-info/METADATA
test_evilaliv3-0.0.5.dist-info/WHEEL
test_evilaliv3-0.0.5.dist-info/entry_points.txt
test_evilaliv3-0.0.5.dist-info/top_level.txt
test_evilaliv3-0.0.5.dist-info/RECORD
